which_fonts_support/__init__.py
which_fonts_support/cli.py
which_fonts_support/main.py
which_fonts_support/preview_server.py
which_fonts_support-2.2.1.dist-info/LICENSE
which_fonts_support-2.2.1.dist-info/METADATA
which_fonts_support-2.2.1.dist-info/WHEEL
which_fonts_support-2.2.1.dist-info/entry_points.txt
which_fonts_support-2.2.1.dist-info/top_level.txt
which_fonts_support-2.2.1.dist-info/RECORD
